aiosubprocess/__init__.py
aiosubprocess/aiosubprocess.py
aiosubprocess-2021.5.3.dist-info/LICENSE
aiosubprocess-2021.5.3.dist-info/WHEEL
aiosubprocess-2021.5.3.dist-info/METADATA
aiosubprocess-2021.5.3.dist-info/RECORD
