Metadata-Version: 2.1
Name: aiosubprocess
Version: 2021.5.3
Summary: A zero-dependency async subprocess that keeps on getting stdout and stderr.
Home-page: https://github.com/Mulugruntz/aiosubprocess
Author: Samuel Giffard
Author-email: samuel@giffard.co
Requires-Python: >=3.6
Classifier: Framework :: AsyncIO
Classifier: License :: OSI Approved :: Apache Software License
Classifier: Natural Language :: English
Classifier: Programming Language :: Python
Classifier: Programming Language :: Python :: 3.6
Classifier: Programming Language :: Python :: 3.7
Classifier: Programming Language :: Python :: 3.8
Classifier: Programming Language :: Python :: 3.9
Classifier: Operating System :: OS Independent
Classifier: Operating System :: MacOS
Classifier: Operating System :: Microsoft :: Windows
Classifier: Operating System :: POSIX
Requires-Dist: pytest ; extra == "dev"
Requires-Dist: coverage ; extra == "dev"
Requires-Dist: pytest-asyncio ; extra == "dev"
Provides-Extra: dev
